{"JtsUTX+nrPiUpQIhVbNh3g==":"mbr-1920x1043.jpg","iF2yY3lLpqDA0FapgCnM2A==":"mbr-1920x1280.jpg","xMYN2Jh98+4e0mYCHvkxsg==":"mbr-1920x1285.jpg","R18Fl0x/+mZUkgEJZLnoeg==":"mbr-1-1920x1280.jpg","UYBiyXyd3/QBZIXHhZHHNg==":"mbr-1920x1125.jpg","MBGVh/hi1+mPEHASXvFBVA==":"mbr-1-1920x1125.jpg","LUBpcZN0ldlgY1X639+jdA==":"mbr-436x291.jpg","5OVPmMVTnVxripkKk8KFug==":"mbr-1920x1276.jpg","am9vt+9GkihZLHKTqKolbA==":"mbr-676x418.jpg","BS9eT2c7k5ZkkVaxmEds3A==":"mbr-436x292.jpg","r7JPCFS0PLgvc7MviD4biQ==":"mbr-616x411.jpg","wwPPltYHhwn+9N5p3cz6cA==":"mbr-1-616x411.jpg","/5TxP6rB5Xsj6wML99MSww==":"logo2.png","lBwGKQ3AD+YBtK54lOH/QA==":"mbr-676x451.jpg","wRL1rFoP9qgBNou8cpFrmw==":"mbr-676x453.jpg","x53rNug+a7k5NQ0iy062Ug==":"mbr-1-676x451.jpg","PqWTMaojfbG45f8/2ZF51w==":"mbr-952x635.jpg"}